architectures/__init__.py
architectures/core/__init__.py
architectures/providers/__init__.py
architectures/providers/aws/__init__.py
architectures/providers/aws/analytics.py
architectures/providers/aws/ar.py
architectures/providers/aws/blockchain.py
architectures/providers/aws/business.py
architectures/providers/aws/compute.py
architectures/providers/aws/cost.py
architectures/providers/aws/database.py
architectures/providers/aws/devtools.py
architectures/providers/aws/enablement.py
architectures/providers/aws/enduser.py
architectures/providers/aws/engagement.py
architectures/providers/aws/game.py
architectures/providers/aws/general.py
architectures/providers/aws/integration.py
architectures/providers/aws/iot.py
architectures/providers/aws/management.py
architectures/providers/aws/media.py
architectures/providers/aws/migration.py
architectures/providers/aws/ml.py
architectures/providers/aws/mobile.py
architectures/providers/aws/network.py
architectures/providers/aws/quantum.py
architectures/providers/aws/robotics.py
architectures/providers/aws/satellite.py
architectures/providers/aws/security.py
architectures/providers/aws/storage.py
architectures/providers/azure/__init__.py
architectures/providers/azure/ai.py
architectures/providers/azure/application.py
architectures/providers/azure/azure.py
architectures/providers/azure/compute.py
architectures/providers/azure/data.py
architectures/providers/azure/deployment.py
architectures/providers/azure/endpoint.py
architectures/providers/azure/general.py
architectures/providers/azure/identity.py
architectures/providers/azure/iot.py
architectures/providers/azure/management.py
architectures/providers/azure/networking.py
architectures/providers/azure/office365.py
architectures/providers/azure/security.py
architectures/providers/azure/storage.py
architectures/providers/gcp/__init__.py
architectures/providers/gcp/analytics.py
architectures/providers/gcp/api.py
architectures/providers/gcp/compute.py
architectures-0.2.7.dist-info/LICENSE
architectures-0.2.7.dist-info/METADATA
architectures-0.2.7.dist-info/WHEEL
architectures-0.2.7.dist-info/top_level.txt
architectures-0.2.7.dist-info/RECORD
