Metadata-Version: 2.1
Name: architectures
Version: 0.2.7
Summary: Tools for creating architecture as code using Python.
Home-page: https://github.com/jsoconno/architectures
Author: Justin O'Connor
Author-email: jsoconno@gmail.com
License: UNKNOWN
Platform: UNKNOWN
Classifier: Programming Language :: Python :: 3
Classifier: License :: OSI Approved :: MIT License
Classifier: Operating System :: OS Independent
Requires-Python: >=3.7
Requires-Dist: graphviz
